<boardgames termsofuse="https://boardgamegeek.com/xmlapi/termsofuse">
     <boardgame objectid="161547">
   <yearpublished>2014</yearpublished>
   <minplayers>2</minplayers>
   <maxplayers>8</maxplayers>
   <playingtime>15</playingtime>
   <minplaytime>15</minplaytime>
   <maxplaytime>15</maxplaytime>
   <age>8</age>
       <name primary="true" sortindex="1">Timeline: Americana</name>
         
   <description>From the first Stetson hat to the unveiling of the first iPad, America's history and its popular culture have gone hand in hand. See if you can remember when the Red Sox traded Babe Ruth, or when Lindbergh crossed the Atlantic. American popular history was never this much fun!_T_E_M_P_T_A_G_lt;br/_T_E_M_P_T_A_G_gt;_T_E_M_P_T_A_G_lt;br/_T_E_M_P_T_A_G_gt;Timeline: Americana takes the players through a historical tour of the popular history of the country. Each player has a hand of cards, and they take turns trying to place those cards correctly into the growing timeline. Guess correctly to get rid of all your cards and win!_T_E_M_P_T_A_G_lt;br/_T_E_M_P_T_A_G_gt;_T_E_M_P_T_A_G_lt;br/_T_E_M_P_T_A_G_gt;Themes included are: Sports, Events, Music, Inventions, and Cinema_T_E_M_P_T_A_G_lt;br/_T_E_M_P_T_A_G_gt;_T_E_M_P_T_A_G_lt;br/_T_E_M_P_T_A_G_gt;</description>
       <thumbnail>https://cf.geekdo-images.com/thumb/img/6SHj89N0QyiQNH2UULjs8uTpG8U=/fit-in/200x150/pic2635907.jpg</thumbnail>
    <image>https://cf.geekdo-images.com/original/img/HZ0TY0K6zsz15qMjtMw-kfLeRFk=/0x0/pic2635907.jpg</image>
      
            <boardgamepublisher objectid="157">Asmodee</boardgamepublisher>
               <boardgamecategory objectid="1002">Card Game</boardgamecategory>
               <boardgameartist objectid="41323">Xavier Collette</boardgameartist>
               <boardgamecategory objectid="1094">Educational</boardgamecategory>
               <boardgamesubdomain objectid="5499">Family Games</boardgamesubdomain>
               <boardgameversion objectid="244365">First edition</boardgameversion>
               <boardgameartist objectid="12935">Nicolas Fructus</boardgameartist>
                      <boardgamedesigner objectid="2617">Frédéric Henry</boardgamedesigner>
                      <boardgamecategory objectid="1030">Party Game</boardgamecategory>
               <boardgamesubdomain objectid="5498">Party Games</boardgamesubdomain>
                             <boardgamefamily objectid="10782">Timeline</boardgamefamily>
               <boardgameintegration objectid="156659">Timeline: 60 ans de télévision à la RTBF</boardgameintegration>
               <boardgameintegration objectid="161546">Timeline: American History</boardgameintegration>
                      <boardgameintegration objectid="255970">Timeline: Canada</boardgameintegration>
               <boardgameintegration objectid="257284">Timeline: Classic</boardgameintegration>
               <boardgameintegration objectid="99975">Timeline: Discoveries</boardgameintegration>
               <boardgameintegration objectid="131325">Timeline: Diversity</boardgameintegration>
               <boardgameintegration objectid="113401">Timeline: Events</boardgameintegration>
               <boardgameintegration objectid="85256">Timeline: Inventions</boardgameintegration>
               <boardgameintegration objectid="145189">Timeline: Music _T_E_M_P_T_A_G_amp; Cinema</boardgameintegration>
               <boardgameintegration objectid="170984">Timeline: Sports et Loisirs</boardgameintegration>
               <boardgamecategory objectid="1027">Trivia</boardgamecategory>
               <boardgameintegration objectid="156659" inbound="true">Timeline: 60 ans de télévision à la RTBF</boardgameintegration>
               <boardgameintegration objectid="161546" inbound="true">Timeline: American History</boardgameintegration>
               <boardgameintegration objectid="255970" inbound="true">Timeline: Canada</boardgameintegration>
               <boardgameintegration objectid="257284" inbound="true">Timeline: Classic</boardgameintegration>
               <boardgameintegration objectid="99975" inbound="true">Timeline: Discoveries</boardgameintegration>
               <boardgameintegration objectid="131325" inbound="true">Timeline: Diversity</boardgameintegration>
               <boardgameintegration objectid="113401" inbound="true">Timeline: Events</boardgameintegration>
               <boardgameintegration objectid="85256" inbound="true">Timeline: Inventions</boardgameintegration>
               <boardgameintegration objectid="145189" inbound="true">Timeline: Music _T_E_M_P_T_A_G_amp; Cinema</boardgameintegration>
               <boardgameintegration objectid="170984" inbound="true">Timeline: Sports et Loisirs</boardgameintegration>
      
   <poll name="suggested_numplayers" title="User Suggested Number of Players" totalvotes="5">
   
  <results numplayers="1">  
     <result value="Best" numvotes="0" />
     <result value="Recommended" numvotes="0" />
     <result value="Not Recommended" numvotes="3" />
    </results>     
   
  <results numplayers="2">  
     <result value="Best" numvotes="0" />
     <result value="Recommended" numvotes="4" />
     <result value="Not Recommended" numvotes="1" />
    </results>     
   
  <results numplayers="3">  
     <result value="Best" numvotes="1" />
     <result value="Recommended" numvotes="4" />
     <result value="Not Recommended" numvotes="0" />
    </results>     
   
  <results numplayers="4">  
     <result value="Best" numvotes="4" />
     <result value="Recommended" numvotes="1" />
     <result value="Not Recommended" numvotes="0" />
    </results>     
   
  <results numplayers="5">  
     <result value="Best" numvotes="1" />
     <result value="Recommended" numvotes="2" />
     <result value="Not Recommended" numvotes="0" />
    </results>     
   
  <results numplayers="6">  
     <result value="Best" numvotes="0" />
     <result value="Recommended" numvotes="3" />
     <result value="Not Recommended" numvotes="0" />
    </results>     
   
  <results numplayers="7">  
     <result value="Best" numvotes="0" />
     <result value="Recommended" numvotes="3" />
     <result value="Not Recommended" numvotes="0" />
    </results>     
   
  <results numplayers="8">  
     <result value="Best" numvotes="0" />
     <result value="Recommended" numvotes="3" />
     <result value="Not Recommended" numvotes="0" />
    </results>     
   
  <results numplayers="8+">  
     <result value="Best" numvotes="0" />
     <result value="Recommended" numvotes="0" />
     <result value="Not Recommended" numvotes="2" />
    </results>     
 </poll>
   <poll name="language_dependence" title="Language Dependence" totalvotes="1">
   
  <results>  
     <result level="1" value="No necessary in-game text" numvotes="0" />
     <result level="2" value="Some necessary text - easily memorized or small crib sheet" numvotes="1" />
     <result level="3" value="Moderate in-game text - needs crib sheet or paste ups" numvotes="0" />
     <result level="4" value="Extensive use of text - massive conversion needed to be playable" numvotes="0" />
     <result level="5" value="Unplayable in another language" numvotes="0" />
    </results>     
 </poll>
   <poll name="suggested_playerage" title="User Suggested Player Age" totalvotes="2">
   <results>  
     <result value="2" numvotes="0" />
     <result value="3" numvotes="0" />
     <result value="4" numvotes="0" />
     <result value="5" numvotes="0" />
     <result value="6" numvotes="0" />
     <result value="8" numvotes="0" />
     <result value="10" numvotes="1" />
     <result value="12" numvotes="1" />
     <result value="14" numvotes="0" />
     <result value="16" numvotes="0" />
     <result value="18" numvotes="0" />
     <result value="21 and up" numvotes="0" />
    </results>     
 </poll>
   
   
      <statistics page="1">
            <ratings >
     <usersrated>789</usersrated>
     <average>6.69691</average>
     <bayesaverage>5.96788</bayesaverage>
     
     <ranks>
       
              <rank type="subtype" id="1" name="boardgame" friendlyname="Board Game Rank" value="2325" bayesaverage="5.96788" />
            
       
              <rank type="family" id="5498" name="partygames" friendlyname="Party Game Rank" value="118" bayesaverage="6.3114" />
              <rank type="family" id="5499" name="familygames" friendlyname="Family Game Rank" value="593" bayesaverage="6.09649" />
            
           </ranks>
     
     <stddev>1.17959</stddev>
     <median>0</median>
     <owned>2166</owned>
     <trading>33</trading>
     <wanting>49</wanting>
     <wishing>136</wishing>
     <numcomments>123</numcomments>
     <numweights>22</numweights>
     <averageweight>1.1364</averageweight>
    </ratings>
               </statistics>
  
    <marketplacehistory>
      <listing>
    <listdate>Fri, 07 Nov 2014 14:04:26 +0000</listdate>
    <saledate>Fri, 07 Nov 2014 14:15:35 +0000</saledate>
    <price currency='USD'>8</price>
    <condition>new</condition>
    <notes>This sale has been auto-generated for the auction: [geekurl=/geeklist/181219/item/3526633#3526633]Item for Geeklist _T_E_M_P_T_A_G_quot;The AUCTION!!!!!! Auction - ends 11/6 in the evening - HUGE Defenders of the Realm lot, Dice Brewing, Panamax, MORE!_T_E_M_P_T_A_G_quot; [/geekurl]
Please do not purchase if you didn_T_E_M_P_T_A_G_#039;t win this auction.
</notes>
   </listing>
      <listing>
    <listdate>Wed, 22 Oct 2014 23:51:24 +0000</listdate>
    <saledate>Fri, 21 Nov 2014 13:40:10 +0000</saledate>
    <price currency='USD'>9.49</price>
    <condition>new</condition>
    <notes>Asmodee (ASMTIM07)
From the first Stetson hat to the unveiling of the first iPad, America_T_E_M_P_T_A_G_#039;s history and its popular culture have gone hand in hand. See if you can remember when the Red Sox traded Babe Ruth, or when Lindbergh crossed the Atlantic. American popular history was never this much fun! Timeline: Americana takes the players through a historical tour of the popular history of the country. Each player has a hand of cards, and they take turns placing those cards correctly into the growing timeline. Guess correctly to get rid of all your cards and win the game!</notes>
   </listing>
      <listing>
    <listdate>Wed, 12 Nov 2014 17:24:52 +0000</listdate>
    <saledate>Sat, 29 Nov 2014 11:44:48 +0000</saledate>
    <price currency='EUR'>12.99</price>
    <condition>new</condition>
    <notes></notes>
   </listing>
      <listing>
    <listdate>Fri, 12 Dec 2014 15:02:59 +0000</listdate>
    <saledate>Sun, 27 Mar 2016 23:46:25 +0000</saledate>
    <price currency='EUR'>13.99</price>
    <condition>new</condition>
    <notes></notes>
   </listing>
      <listing>
    <listdate>Thu, 05 Jul 2018 04:08:42 +0000</listdate>
    <saledate>Thu, 26 Jul 2018 19:50:49 +0000</saledate>
    <price currency='USD'>8.89</price>
    <condition>likenew</condition>
    <notes></notes>
   </listing>
     </marketplacehistory>   
  
    
  </boardgame>
 </boardgames>
